tumblr_2_album/__init__.py
tumblr_2_album-0.0.40.dist-info/LICENSE
tumblr_2_album-0.0.40.dist-info/METADATA
tumblr_2_album-0.0.40.dist-info/WHEEL
tumblr_2_album-0.0.40.dist-info/top_level.txt
tumblr_2_album-0.0.40.dist-info/RECORD
