Metadata-Version: 2.1
Name: tumblr-2-album
Version: 0.0.40
Summary: Return photo list and caption (markdown format) from tumblr.
Home-page: https://github.com/gaoyunzhi/tumblr_2_album
Author: Yunzhi Gao
Author-email: gaoyunzhi@gmail.com
License: UNKNOWN
Platform: UNKNOWN
Classifier: Programming Language :: Python :: 3
Classifier: License :: OSI Approved :: MIT License
Classifier: Operating System :: OS Independent
Requires-Python: >=3.0
License-File: LICENSE
Requires-Dist: telegram-util
Requires-Dist: bs4
Requires-Dist: pytumblr
Requires-Dist: cached-url
